[1,["15301313b","ecpdLyjvZBwrvm+cedCcQy","1a6fbQwWJPzJdcl419N3wm","11QNQZ3A9Bnrmfd8YpbCLk"],["node","_textureSetter","_spriteFrame","root","data"],[["cc.Node",["_name","_groupIndex","_components","_prefab","_contentSize","_parent","_children","_trs"],1,9,4,5,1,2,7],"cc.SpriteFrame",["cc.Prefab",["_name"],2],["cc.BoxCollider",["node","_size"],3,1,5],["0afdbuIudJG17Ubeb9JdadQ",["node"],3,1],["cc.PrefabInfo",["fileId","root"],2,1],["cc.Sprite",["node","_materials","_spriteFrame"],3,1,3,6]],[[5,0,1,2],[6,0,1,2,1],[2,0,2],[0,0,1,6,2,3,4,3],[0,0,1,5,2,3,4,3],[0,0,1,5,2,3,4,7,3],[3,0,1,1],[4,0,1]],[[[{"name":"imageglass_alphapuzzle","rect":[448,706,117,131],"offset":[0,0],"originalSize":[117,131],"rotated":1,"capInsets":[0,0,0,0]}],[1],0,[0],[1],[0]],[[{"name":"placeholder_alphapuzzle","rect":[164,706,119,137],"offset":[-1,-0.5],"originalSize":[123,138],"rotated":1,"capInsets":[0,0,0,0]}],[1],0,[0],[1],[0]],[[[2,"imagePuzzleDrop"],[3,"imagePuzzleDrop",9,[-4,-5],[[6,-2,[5,50,50]],[7,-3]],[0,"ffBHb2TohK57Vtpg/oI6TW",-1],[5,120,400]],[4,"placeholder_alphapuzzle",9,1,[[1,-6,[0],1]],[0,"1b58JiQplGq7TGrnTT0xYH",1],[5,120,137]],[5,"imageglass_alphapuzzle",9,1,[[1,-7,[2],3]],[0,"b70LPgAXhLNa5Y9+Lu4a++",1],[5,117,131],[0,131,0,0,0,0,1,1,1,1]]],0,[0,3,1,0,0,1,0,0,1,0,-1,2,0,-2,3,0,0,2,0,0,3,0,4,1,7],[0,0,0,0],[-1,2,-1,2],[1,2,1,3]]]]