[1,["ecpdLyjvZBwrvm+cedCcQy","133fc0633","6eBWFz0oVHPLIGQKf/9Thu","5aPgU5VM9MIroPFT6S1OFT","8c20Sso/ZEn7NUfNSM+EBh"],["node","_textureSetter","_spriteFrame","root","pattern","data"],["cc.SpriteFrame",["cc.Sprite",["_sizeMode","node","_materials","_spriteFrame"],2,1,3,6],["cc.Prefab",["_name"],2],["cc.Node",["_name","_groupIndex","_children","_components","_prefab","_contentSize","_anchorPoint"],1,2,9,4,5,5],["cc.Node",["_name","_groupIndex","_parent","_components","_prefab","_contentSize","_trs"],1,1,2,4,5,7],["cc.BoxCollider",["node","_offset","_size"],3,1,5,5],["96333ZTyOhGy6Vt492j+m1D",["multipleDrags","node","pattern"],2,1,1],["cc.PrefabInfo",["fileId","root"],2,1]],[[7,0,1,2],[2,0,2],[3,0,1,2,3,4,5,6,3],[4,0,1,2,3,4,5,6,3],[1,0,1,2,3,2],[1,1,2,1],[5,0,1,2,1],[6,0,1,2,2]],[[[{"name":"box_answer_soundtrain","rect":[3,638,146,146],"offset":[0,0],"originalSize":[146,146],"capInsets":[0,0,0,0]}],[0],0,[0],[1],[1]],[[{"name":"default_sprite","rect":[0,2,40,36],"offset":[0,0],"originalSize":[40,40],"capInsets":[0,0,0,0]}],[0],0,[0],[1],[2]],[[[1,"patterntrainDrag"],[2,"patterntrainDrag",8,[-6],[[4,0,-2,[1],2],[6,-3,[0,0,38],[5,74,76]],[7,true,-5,-4]],[0,"4bUlzTgutCXK+PblIStCgb",-1],[5,140,140],[0,0.5,0]],[3,"pattern",8,1,[-7],[0,"ed4su5JIlIBYSzC6tb3Y21",1],[5,40,36],[0,70,0,0,0,0,1,1,1,1]],[5,2,[0]]],0,[0,3,1,0,0,1,0,0,1,0,4,3,0,0,1,0,-1,2,0,-1,3,0,5,1,7],[0,0,0,3],[-1,-1,2,2],[0,0,3,4]]]]